pyxml2dict.py
pyxml2dict-1.0.3.dist-info/LICENSE
pyxml2dict-1.0.3.dist-info/METADATA
pyxml2dict-1.0.3.dist-info/WHEEL
pyxml2dict-1.0.3.dist-info/top_level.txt
pyxml2dict-1.0.3.dist-info/RECORD
