Metadata-Version: 2.1
Name: pyxml2dict
Version: 1.0.3
Summary: Convert XML to python Dict
Home-page: https://github.com/mjrao/pyxml2dict
Author: mjrao
Author-email: mjrao@foxmail.com
License: GPL-3.0
Keywords: xml2dict pyxml2dict
Platform: UNKNOWN
